progressive_samplers/__init__.py
progressive_samplers/_nbdev.py
progressive_samplers/core.py
progressive_samplers/test.py
progressive_samplers-0.0.79.dist-info/LICENSE
progressive_samplers-0.0.79.dist-info/METADATA
progressive_samplers-0.0.79.dist-info/WHEEL
progressive_samplers-0.0.79.dist-info/entry_points.txt
progressive_samplers-0.0.79.dist-info/top_level.txt
progressive_samplers-0.0.79.dist-info/RECORD
