Metadata-Version: 2.1
Name: progressive-samplers
Version: 0.0.79
Summary: A collection of general-purpose Progressive Samplers (Latin-Hypercube, Jittered, Multi Jittered, etc). Mainly for Hyperparameter search
Home-page: https://github.com/ELC/progressive_samplers/tree/master/
Author: Ezequiel Castaño
Author-email: castanoezequielleonardo@gmail.com
License: Apache Software License 2.0
Keywords: samplers,hyperparameter,search
Platform: UNKNOWN
Classifier: Development Status :: 2 - Pre-Alpha
Classifier: Intended Audience :: Developers
Classifier: License :: OSI Approved :: Apache Software License
Classifier: Natural Language :: English
Classifier: Programming Language :: Python :: 3.6
Classifier: Programming Language :: Python :: 3.7
Classifier: Programming Language :: Python :: 3.8
Classifier: Programming Language :: Python :: 3.9
Requires-Python: >=3.6
Requires-Dist: numpy (>=1.19.2)
Requires-Dist: matplotlib (>=3.3.2)
